supadata/__init__.py
supadata/client.py
supadata/errors.py
supadata/types.py
supadata/web.py
supadata/youtube.py
supadata-1.4.0.dist-info/METADATA
supadata-1.4.0.dist-info/WHEEL
supadata-1.4.0.dist-info/licenses/LICENSE
supadata-1.4.0.dist-info/RECORD
