Metadata-Version: 2.4
Name: supadata
Version: 1.4.0
Summary: The official Python SDK for Supadata - scrape web and YouTube content with ease
Project-URL: homepage, https://supadata.ai
Project-URL: repository, https://github.com/supadata/py
Project-URL: documentation, https://supadata.ai/documentation
Author-email: Supadata <support@supadata.ai>
License-Expression: MIT
License-File: LICENSE
Keywords: ai,api,llm,supadata,transcripts,web-scraping,youtube
Classifier: License :: OSI Approved :: MIT License
Classifier: Operating System :: OS Independent
Classifier: Programming Language :: Python :: 3
Requires-Python: >=3.7
Requires-Dist: requests>=2.28.1
Provides-Extra: test
Requires-Dist: pytest>=7.0.0; extra == 'test'
Requires-Dist: requests-mock>=1.11.0; extra == 'test'
